MicroInverse/MicroInverse_examples.py
MicroInverse/MicroInverse_utils.py
MicroInverse/__init__.py
MicroInverse/adv_diff_fipy_solve_1000_vel0.05_r005_dx5000_dt1000.npz
MicroInverse/cli.py
MicroInverse/dist.py
MicroInverse/tests/adv_diff_fipy_solve_1000_vel0.05_r005_dx5000_dt1000.npz
MicroInverse-0.3.0.dist-info/METADATA
MicroInverse-0.3.0.dist-info/RECORD
MicroInverse-0.3.0.dist-info/WHEEL
MicroInverse-0.3.0.dist-info/entry_points.txt
MicroInverse-0.3.0.dist-info/top_level.txt
