Metadata-Version: 2.1
Name: MicroInverse
Version: 0.3.0
Summary: MicroInverse is a Python package for inversion of a transport operator from tracer data.
Home-page: https://github.com/AleksiNummelin/MicroInverse
Author: Aleksi Nummelin
Author-email: aleksi.h.nummelin@gmail.com
License: MIT license
Keywords: MicroInverse
Platform: UNKNOWN
Classifier: Development Status :: 2 - Pre-Alpha
Classifier: Intended Audience :: Developers
Classifier: License :: OSI Approved :: MIT License
Classifier: Natural Language :: English
Classifier: Programming Language :: Python :: 2
Classifier: Programming Language :: Python :: 2.7
Classifier: Programming Language :: Python :: 3.6
Classifier: Operating System :: OS Independent
Requires-Dist: Click (>=6.0)
Requires-Dist: scipy (>=1.0.0)
Requires-Dist: numpy (>=1.14.2)
Requires-Dist: joblib (>=0.11)
Requires-Dist: xarray (>=0.10.2)
Requires-Dist: matplotlib (>=2.2.2)
